<?xml version="1.0" encoding="UTF-8"?>
<beans xmlns="http://www.springframework.org/schema/beans"
       xmlns:context="http://www.springframework.org/schema/context"
       xmlns:xsi="http://www.w3.org/2001/XMLSchema-instance"
       xsi:schemaLocation="http://www.springframework.org/schema/beans
    http://www.springframework.org/schema/beans/spring-beans-3.0.xsd
    http://www.springframework.org/schema/context
    http://www.springframework.org/schema/context/spring-context-3.0.xsd">

    <context:annotation-config/>
    <bean id="transactionManager"
          class="org.springframework.orm.hibernate4.HibernateTransactionManager">
        <property name="sessionFactory" ref="sessionFactory"/>
    </bean>

    <bean id="dataSource"
          class="org.springframework.jdbc.datasource.DriverManagerDataSource">
        <property name="driverClassName" value="org.postgresql.Driver"/>
        <property name="url" value="jdbc:postgresql://localhost:5432/InterestIn"/>
        <property name="username" value="interestin"/>
        <property name="password" value="interestin"/>
    </bean>

    <bean id="sessionFactory"
          class="org.springframework.orm.hibernate4.LocalSessionFactoryBean">
        <property name="dataSource" ref="dataSource"/>
        <property name="hibernateProperties">
            <props>
                <prop key="hibernate.dialect">org.hibernate.dialect.PostgreSQL81Dialect</prop>
                <prop key="hibernate.show_sql">true</prop>
                <prop key="hibernate.format_sql">false</prop>
                <prop key="hibernate.hbm2ddl.auto">create</prop>
            </props>
        </property>
        <property name="annotatedClasses">
            <list>
                <value>com.interestin.model.User</value>
                <value>com.interestin.model.UserActivation</value>
                <value>com.interestin.model.UserProfile</value>
                <value>com.interestin.model.Hobby</value>
                <value>com.interestin.model.Country</value>
                <value>com.interestin.model.City</value>
            </list>
        </property>
    </bean>
</beans>
